mo9mo9db/__init__.py
mo9mo9db/base_mixin.py
mo9mo9db/dbconfig.py
mo9mo9db/dbsession.py
mo9mo9db/dbtables.py
mo9mo9db-0.1.0.dist-info/METADATA
mo9mo9db-0.1.0.dist-info/WHEEL
mo9mo9db-0.1.0.dist-info/top_level.txt
mo9mo9db-0.1.0.dist-info/RECORD
