Metadata-Version: 2.1
Name: mo9mo9db
Version: 0.1.0
Summary: discord.guild[mo9mo9study]でDBと連携するために使用するモジュール
Home-page: https://github.com/mo9mo9study/discord.db
Author: supleiades
Author-email: su.impreza.itengineer@gmail.com
License: UNKNOWN
Platform: UNKNOWN
Requires-Dist: PyMySQL
Requires-Dist: python-dotenv
Requires-Dist: SQLAlchemy-Utils (==0.36.8)
Requires-Dist: SQLAlchemy (==1.3.23)
